nikefy/__init__.py
nikefy/__main__.py
nikefy/_version.py
nikefy/nikefy.py
nikefy/tests/test_all.py
nikefy-0.0.1.dist-info/LICENSE
nikefy-0.0.1.dist-info/METADATA
nikefy-0.0.1.dist-info/WHEEL
nikefy-0.0.1.dist-info/top_level.txt
nikefy-0.0.1.dist-info/RECORD
